{
  "services": [
    {
      "notifications": true,
      "count_message_direct": 0,
      "count_message_indirect": 0,
      "zoom": 0,
      "showIndirectMessages": true,
      "enabled": true,
      "focusMode": true,
      "customURL": false,
      "custom_icon": "https://slack-files2.s3-us-west-2.amazonaws.com/avatars/2016-01-13/18387782098_877d1a6fc4f2c820e555_88.png",
      "id": "e403f9e9-1076-9c43-a903-8aabd8a53ef0",
      "mute_audio": false,
      "name": "",
      "order": 2,
      "service": "slack",
      "team": "tenforcesemtech"
    },
    {
      "notifications": true,
      "count_message_direct": 0,
      "count_message_indirect": 0,
      "zoom": 0,
      "showIndirectMessages": true,
      "enabled": true,
      "focusMode": true,
      "customURL": false,
      "id": "75821f4f-2fb3-e797-c242-bb2af8550131",
      "mute_audio": false,
      "name": "",
      "order": 1,
      "service": "skype"
    },
    {
      "notifications": true,
      "count_message_direct": 0,
      "count_message_indirect": 0,
      "zoom": 0,
      "showIndirectMessages": true,
      "enabled": true,
      "focusMode": true,
      "customURL": false,
      "custom_icon": "https://slack-files2.s3-us-west-2.amazonaws.com/avatars/2016-08-08/67127715942_d2157161757d4d16ca6f_88.png",
      "id": "ee42a00b-86da-0b5a-b05f-80bc707c2328",
      "mute_audio": false,
      "name": "",
      "order": 3,
      "service": "slack",
      "team": "bme-db-lab"
    },
    {
      "notifications": false,
      "count_message_direct": 0,
      "count_message_indirect": 0,
      "zoom": 0,
      "showIndirectMessages": true,
      "enabled": true,
      "focusMode": true,
      "customURL": false,
      "id": "ce145974-e164-8310-cc5d-c4045d5903ba",
      "mute_audio": false,
      "name": "",
      "order": 4,
      "service": "whatsapp"
    },
    {
      "notifications": false,
      "count_message_direct": 0,
      "count_message_indirect": 0,
      "zoom": 0,
      "showIndirectMessages": true,
      "enabled": true,
      "focusMode": true,
      "customURL": false,
      "id": "c0e4222a-bc9c-2eae-c2a3-938205d5bcd5",
      "mute_audio": false,
      "name": "",
      "order": 5,
      "service": "messenger"
    },
    {
      "notifications": false,
      "count_message_direct": 0,
      "count_message_indirect": 0,
      "zoom": 0,
      "showIndirectMessages": false,
      "enabled": true,
      "focusMode": true,
      "id": "f0dff3bc-d1b6-afec-825d-93f455d12172",
      "order": 6,
      "service": "slack",
      "name": "",
      "mute_audio": true,
      "customURL": false,
      "team": "embercommunity",
      "custom_icon": "https://slack-files2.s3-us-west-2.amazonaws.com/avatars/2015-03-26/4207606557_6211decb4c88966c84cd_88.jpg"
    }
  ]
}